{"actions": 11639, "added_lines": 901817.0, "added_lines_30": 3616.0, "added_lines_365": 267688.0, "added_lines_7": 172.0, "authors": 87, "authors_30": 1, "authors_365": 1, "authors_7": 1, "avg_commits_author": 37.24, "avg_commits_month": 98.91, "avg_files_author": 79.27, "avg_files_month": 210.56, "branches": 14, "commits": 977, "commits_30": 42, "commits_365": 923, "commits_7": 8, "committers": 77, "diff_netadded_lines_30": -921.0, "diff_netadded_lines_365": -12996.0, "diff_netadded_lines_7": -1282.0, "diff_netauthors_30": 0, "diff_netauthors_365": 0, "diff_netauthors_7": 0, "diff_netcommits_30": -10, "diff_netcommits_365": 832, "diff_netcommits_7": -8, "diff_netfiles_30": -91, "diff_netfiles_365": -1367, "diff_netfiles_7": -44, "diff_netnewauthors_30": -5, "diff_netnewauthors_365": -6, "diff_netnewauthors_7": 0, "diff_netremoved_lines_30": -1697.0, "diff_netremoved_lines_365": 41397.0, "diff_netremoved_lines_7": -1329.0, "files": 6738, "files_30": 79, "files_365": 992, "files_7": 10, "first_date": "2016-03-03", "last_date": "2016-04-01", "newauthors": 87, "newauthors_30": 0, "newauthors_365": 37, "newauthors_7": 0, "percentage_added_lines_30": 20, "percentage_added_lines_365": 4, "percentage_added_lines_7": 88, "percentage_authors_30": 0, "percentage_authors_365": 0, "percentage_authors_7": 0, "percentage_commits_30": 19, "percentage_commits_365": 914, "percentage_commits_7": 50, "percentage_files_30": 53, "percentage_files_365": 57, "percentage_files_7": 81, "percentage_newauthors_30": 100, "percentage_newauthors_365": 13, "percentage_newauthors_7": 0, "percentage_removed_lines_30": 31, "percentage_removed_lines_365": 166, "percentage_removed_lines_7": 93, "removed_lines": 124319.0, "removed_lines_30": 3622.0, "removed_lines_365": 66190.0, "removed_lines_7": 87.0, "repositories": 37}