{"abandoned": 313, "abandoned_30": 7, "abandoned_365": 107, "abandoned_7": 2, "bmiscr_30": 0, "bmiscr_365": 0, "bmiscr_7": 0, "closed": 1602, "closers": 169, "closers_30": 11, "closers_365": 85, "closers_7": 4, "diff_netabandoned_30": 0, "diff_netabandoned_365": -97, "diff_netabandoned_7": 0, "diff_netbmiscr_30": -1, "diff_netbmiscr_365": 0, "diff_netbmiscr_7": -1, "diff_netclosers_30": 0, "diff_netclosers_365": -13, "diff_netclosers_7": 1, "diff_netmerged_30": -4, "diff_netmerged_365": -395, "diff_netmerged_7": -1, "diff_netmergers_30": 1, "diff_netmergers_365": 9, "diff_netmergers_7": 3, "diff_netparticipants_30": 1, "diff_netparticipants_365": -13, "diff_netparticipants_7": 3, "diff_netsubmitted_30": 0, "diff_netsubmitted_365": -492, "diff_netsubmitted_7": 3, "diff_netsubmitters_30": 0, "diff_netsubmitters_365": -15, "diff_netsubmitters_7": -1, "first_date": "2013-08-10", "last_date": "2016-01-15", "merged": 1289, "merged_30": 7, "merged_365": 373, "merged_7": 2, "mergers": 16, "mergers_30": 5, "mergers_365": 15, "mergers_7": 4, "participants": 227, "participants_30": 24, "participants_365": 123, "participants_7": 15, "pending": 21, "percentage_abandoned_30": 0, "percentage_abandoned_365": 47, "percentage_abandoned_7": 0, "percentage_bmiscr_30": 100, "percentage_bmiscr_365": 0, "percentage_bmiscr_7": 100, "percentage_closers_30": 0, "percentage_closers_365": 13, "percentage_closers_7": 33, "percentage_merged_30": 36, "percentage_merged_365": 51, "percentage_merged_7": 33, "percentage_mergers_30": 25, "percentage_mergers_365": 150, "percentage_mergers_7": 300, "percentage_participants_30": 4, "percentage_participants_365": 9, "percentage_participants_7": 25, "percentage_submitted_30": 0, "percentage_submitted_365": 50, "percentage_submitted_7": 75, "percentage_submitters_30": 0, "percentage_submitters_365": 14, "percentage_submitters_7": 25, "repositories": 1, "submitted": 1623, "submitted_30": 16, "submitted_365": 490, "submitted_7": 7, "submitters": 173, "submitters_30": 11, "submitters_365": 86, "submitters_7": 3, "timeto_close_avg": 5.47, "timeto_close_median": 0.85, "timeto_merge_avg": 3.13, "timeto_merge_median": 0.73}